shapely_cli/cli.py
shapely_cli/eval.py
shapely_cli/helpers.py
shapely_cli-0.2.0.dist-info/LICENSE
shapely_cli-0.2.0.dist-info/METADATA
shapely_cli-0.2.0.dist-info/WHEEL
shapely_cli-0.2.0.dist-info/entry_points.txt
shapely_cli-0.2.0.dist-info/top_level.txt
shapely_cli-0.2.0.dist-info/RECORD
