Metadata-Version: 2.2
Name: shapely-cli
Version: 0.2.0
Summary: A command line tool for operating on GeoJSON objects with Shapely
Author-email: Jake Low <hello@jakelow.com>
Project-URL: Repository, https://github.com/jake-low/shapely-cli
Classifier: Programming Language :: Python :: 3
Classifier: License :: OSI Approved :: ISC License (ISCL)
Classifier: Operating System :: OS Independent
License-File: LICENSE
Requires-Dist: click
Requires-Dist: shapely>=2.0.0
Requires-Dist: pyproj>=3.6.0
Requires-Dist: numpy
